{
  "Layout": [
    {
      "time": 1,
      "event": 4,
      "yaxis": 100,
	  "xstop": 900,
	  "ystop": 800
    },
    {
      "time": 1,
      "event": 1,
      "yaxis": 200
    },
    {
      "time": 1,
      "event": 1,
      "yaxis": 225
    },
	    {
      "time": 1,
      "event": 1,
      "yaxis": 250
    },
    {
      "time": 1,
      "event": 1,
      "yaxis": 275
    },
    {
      "time": 2,
      "event": 2,
      "yaxis": 200
    },
    {
      "time": 3,
      "event": 3,
      "yaxis": 300
    }
  ]
}